LICENSE
MANIFEST.in
setup.cfg
setup.py
Flask_Enterprise.egg-info/PKG-INFO
Flask_Enterprise.egg-info/SOURCES.txt
Flask_Enterprise.egg-info/dependency_links.txt
Flask_Enterprise.egg-info/namespace_packages.txt
Flask_Enterprise.egg-info/not-zip-safe
Flask_Enterprise.egg-info/requires.txt
Flask_Enterprise.egg-info/top_level.txt
docs/Makefile
docs/conf.py
docs/index.rst
docs/make.bat
docs/_static/flask-enterprise.png
docs/_themes/.gitignore
docs/_themes/LICENSE
docs/_themes/README
docs/_themes/flask_theme_support.py
docs/_themes/flask_small/layout.html
docs/_themes/flask_small/theme.conf
docs/_themes/flask_small/static/MyriadPro-Light.otf
docs/_themes/flask_small/static/flasky.css_t
example/soap.py
example/xmlrpc.py
flaskext/__init__.py
flaskext/enterprise.py