Metadata-Version: 1.0
Name: Flask-Enterprise
Version: 1.0
Summary: Enterprise capabilities for Flask
Home-page: http://massive.immersedcode.org/2011/staging/projects/default/python/flask-enterprise/
Author: Massive of Rock Inc.
Author-email: UNKNOWN
License: CDDL
Platform: any
Classifier: Development Status :: 4 - Beta
Classifier: Environment :: Web Environment
Classifier: Intended Audience :: Developers
Classifier: Operating System :: OS Independent
Classifier: Programming Language :: Python
Classifier: Topic :: Internet :: WWW/HTTP :: Dynamic Content
Classifier: Topic :: Software Development :: Libraries :: Python Modules
